pymaesh/__init__.py
pymaesh/algorithms/__init__.py
pymaesh/algorithms/build.py
pymaesh/algorithms/func.py
pymaesh/algorithms/generate.py
pymaesh/algorithms/stats.py
pymaesh/backend/__init__.py
pymaesh/backend/base.py
pymaesh/backend/numpy.py
pymaesh/utils/__init__.py
pymaesh/utils/numpy.py
pymaesh/walker/__init__.py
pymaesh/walker/base.py
pymaesh/walker/node2vec.py
tests/__init__.py
tests/build_tests.py
tests/stats_tests.py
pymaesh-0.1.0.dist-info/LICENSE
pymaesh-0.1.0.dist-info/METADATA
pymaesh-0.1.0.dist-info/WHEEL
pymaesh-0.1.0.dist-info/top_level.txt
pymaesh-0.1.0.dist-info/RECORD
