Metadata-Version: 2.1
Name: pymaesh
Version: 0.1.0
Summary: Utilities for Analyzing Graphs in Python.
Home-page: https://github.com/borchero/pymaesh
Author: Oliver Borchert
Author-email: borchero@icloud.com
License: License :: OSI Approved :: MIT License
Platform: UNKNOWN
Classifier: Development Status :: 4 - Beta
Classifier: Programming Language :: Python :: 3.7
Classifier: Topic :: Software Development :: Libraries
Requires-Python: >=3.7
Requires-Dist: numpy (<2.0.0,>=1.18.2)
Requires-Dist: scipy (<2.0.0,>=1.4.1)
Requires-Dist: numba (<0.49.0,>=0.48.0)
